{
  "$schema": "http://json-schema.org/draft-07/schema",
  "additionalProperties": false,
  "properties": {
    "allow": { "type": "string", "default": "Allow" },
    "block": { "type": "string", "default": "Block" },
    "cancel": { "type": "string", "default": "Cancel" },
    "category_restrictions": { "type": "string", "default": "Category restrictions" },
    "clear_filters": { "type": "string", "default": "Clear filters" },
    "close": { "type": "string", "default": "Close" },
    "code": { "type": "string", "default": "Code" },
    "code_plural": { "type": "string", "default": "Codes" },
    "confirm": { "type": "string", "default": "Confirm" },
    "create": { "type": "string", "default": "Create" },
    "currency": { "type": "string", "default": "Currency" },
    "currency_aed": { "type": "string", "default": "United Arab Emirates Dirham" },
    "currency_afn": { "type": "string", "default": "Afghan Afghani" },
    "currency_all": { "type": "string", "default": "Albanian Lek" },
    "currency_amd": { "type": "string", "default": "Armenian Dram" },
    "currency_ang": { "type": "string", "default": "Netherlands Antillean Guilder" },
    "currency_aoa": { "type": "string", "default": "Angolan Kwanza" },
    "currency_ars": { "type": "string", "default": "Argentine Peso" },
    "currency_aud": { "type": "string", "default": "Australian Dollar" },
    "currency_awg": { "type": "string", "default": "Aruban Florin" },
    "currency_azn": { "type": "string", "default": "Azerbaijani Manat" },
    "currency_bam": { "type": "string", "default": "Bosnia-Herzegovina Convertible Mark" },
    "currency_bbd": { "type": "string", "default": "Barbadian Dollar" },
    "currency_bdt": { "type": "string", "default": "Bangladeshi Taka" },
    "currency_bgn": { "type": "string", "default": "Bulgarian Lev" },
    "currency_bhd": { "type": "string", "default": "Bahraini Dinar" },
    "currency_bif": { "type": "string", "default": "Burundian Franc" },
    "currency_bmd": { "type": "string", "default": "Bermudan Dollar" },
    "currency_bnd": { "type": "string", "default": "Brunei Dollar" },
    "currency_bob": { "type": "string", "default": "Bolivian Boliviano" },
    "currency_brl": { "type": "string", "default": "Brazilian Real" },
    "currency_bsd": { "type": "string", "default": "Bahamian Dollar" },
    "currency_btc": { "type": "string", "default": "Bitcoin" },
    "currency_btn": { "type": "string", "default": "Bhutanese Ngultrum" },
    "currency_bwp": { "type": "string", "default": "Botswanan Pula" },
    "currency_byn": { "type": "string", "default": "Belarusian Ruble" },
    "currency_bzd": { "type": "string", "default": "Belize Dollar" },
    "currency_cad": { "type": "string", "default": "Canadian Dollar" },
    "currency_cdf": { "type": "string", "default": "Congolese Franc" },
    "currency_chf": { "type": "string", "default": "Swiss Franc" },
    "currency_clf": { "type": "string", "default": "Chilean Unit of Account (UF)" },
    "currency_clp": { "type": "string", "default": "Chilean Peso" },
    "currency_cnh": { "type": "string", "default": "Chinese Yuan (Offshore)" },
    "currency_cny": { "type": "string", "default": "Chinese Yuan" },
    "currency_cop": { "type": "string", "default": "Colombian Peso" },
    "currency_crc": { "type": "string", "default": "Costa Rican Colón" },
    "currency_cuc": { "type": "string", "default": "Cuban Convertible Peso" },
    "currency_cup": { "type": "string", "default": "Cuban Peso" },
    "currency_cve": { "type": "string", "default": "Cape Verdean Escudo" },
    "currency_czk": { "type": "string", "default": "Czech Republic Koruna" },
    "currency_djf": { "type": "string", "default": "Djiboutian Franc" },
    "currency_dkk": { "type": "string", "default": "Danish Krone" },
    "currency_dop": { "type": "string", "default": "Dominican Peso" },
    "currency_dzd": { "type": "string", "default": "Algerian Dinar" },
    "currency_egp": { "type": "string", "default": "Egyptian Pound" },
    "currency_ern": { "type": "string", "default": "Eritrean Nakfa" },
    "currency_etb": { "type": "string", "default": "Ethiopian Birr" },
    "currency_eur": { "type": "string", "default": "Euro" },
    "currency_fjd": { "type": "string", "default": "Fijian Dollar" },
    "currency_fkp": { "type": "string", "default": "Falkland Islands Pound" },
    "currency_gbp": { "type": "string", "default": "British Pound Sterling" },
    "currency_gel": { "type": "string", "default": "Georgian Lari" },
    "currency_ggp": { "type": "string", "default": "Guernsey Pound" },
    "currency_ghs": { "type": "string", "default": "Ghanaian Cedi" },
    "currency_gip": { "type": "string", "default": "Gibraltar Pound" },
    "currency_gmd": { "type": "string", "default": "Gambian Dalasi" },
    "currency_gnf": { "type": "string", "default": "Guinean Franc" },
    "currency_gtq": { "type": "string", "default": "Guatemalan Quetzal" },
    "currency_gyd": { "type": "string", "default": "Guyanaese Dollar" },
    "currency_hkd": { "type": "string", "default": "Hong Kong Dollar" },
    "currency_hnl": { "type": "string", "default": "Honduran Lempira" },
    "currency_hrk": { "type": "string", "default": "Croatian Kuna" },
    "currency_htg": { "type": "string", "default": "Haitian Gourde" },
    "currency_huf": { "type": "string", "default": "Hungarian Forint" },
    "currency_idr": { "type": "string", "default": "Indonesian Rupiah" },
    "currency_ils": { "type": "string", "default": "Israeli New Sheqel" },
    "currency_imp": { "type": "string", "default": "Manx pound" },
    "currency_inr": { "type": "string", "default": "Indian Rupee" },
    "currency_iqd": { "type": "string", "default": "Iraqi Dinar" },
    "currency_irr": { "type": "string", "default": "Iranian Rial" },
    "currency_isk": { "type": "string", "default": "Icelandic Króna" },
    "currency_jep": { "type": "string", "default": "Jersey Pound" },
    "currency_jmd": { "type": "string", "default": "Jamaican Dollar" },
    "currency_jod": { "type": "string", "default": "Jordanian Dinar" },
    "currency_jpy": { "type": "string", "default": "Japanese Yen" },
    "currency_kes": { "type": "string", "default": "Kenyan Shilling" },
    "currency_kgs": { "type": "string", "default": "Kyrgystani Som" },
    "currency_khr": { "type": "string", "default": "Cambodian Riel" },
    "currency_kmf": { "type": "string", "default": "Comorian Franc" },
    "currency_kpw": { "type": "string", "default": "North Korean Won" },
    "currency_krw": { "type": "string", "default": "South Korean Won" },
    "currency_kwd": { "type": "string", "default": "Kuwaiti Dinar" },
    "currency_kyd": { "type": "string", "default": "Cayman Islands Dollar" },
    "currency_kzt": { "type": "string", "default": "Kazakhstani Tenge" },
    "currency_lak": { "type": "string", "default": "Laotian Kip" },
    "currency_lbp": { "type": "string", "default": "Lebanese Pound" },
    "currency_lkr": { "type": "string", "default": "Sri Lankan Rupee" },
    "currency_lrd": { "type": "string", "default": "Liberian Dollar" },
    "currency_lsl": { "type": "string", "default": "Lesotho Loti" },
    "currency_lyd": { "type": "string", "default": "Libyan Dinar" },
    "currency_mad": { "type": "string", "default": "Moroccan Dirham" },
    "currency_mdl": { "type": "string", "default": "Moldovan Leu" },
    "currency_mga": { "type": "string", "default": "Malagasy Ariary" },
    "currency_mkd": { "type": "string", "default": "Macedonian Denar" },
    "currency_mmk": { "type": "string", "default": "Myanma Kyat" },
    "currency_mnt": { "type": "string", "default": "Mongolian Tugrik" },
    "currency_mop": { "type": "string", "default": "Macanese Pataca" },
    "currency_mru": { "type": "string", "default": "Mauritanian Ouguiya" },
    "currency_mur": { "type": "string", "default": "Mauritian Rupee" },
    "currency_mvr": { "type": "string", "default": "Maldivian Rufiyaa" },
    "currency_mwk": { "type": "string", "default": "Malawian Kwacha" },
    "currency_mxn": { "type": "string", "default": "Mexican Peso" },
    "currency_myr": { "type": "string", "default": "Malaysian Ringgit" },
    "currency_mzn": { "type": "string", "default": "Mozambican Metical" },
    "currency_nad": { "type": "string", "default": "Namibian Dollar" },
    "currency_ngn": { "type": "string", "default": "Nigerian Naira" },
    "currency_nio": { "type": "string", "default": "Nicaraguan Córdoba" },
    "currency_nok": { "type": "string", "default": "Norwegian Krone" },
    "currency_npr": { "type": "string", "default": "Nepalese Rupee" },
    "currency_nzd": { "type": "string", "default": "New Zealand Dollar" },
    "currency_omr": { "type": "string", "default": "Omani Rial" },
    "currency_pab": { "type": "string", "default": "Panamanian Balboa" },
    "currency_pen": { "type": "string", "default": "Peruvian Nuevo Sol" },
    "currency_pgk": { "type": "string", "default": "Papua New Guinean Kina" },
    "currency_php": { "type": "string", "default": "Philippine Peso" },
    "currency_pkr": { "type": "string", "default": "Pakistani Rupee" },
    "currency_pln": { "type": "string", "default": "Polish Zloty" },
    "currency_pyg": { "type": "string", "default": "Paraguayan Guarani" },
    "currency_qar": { "type": "string", "default": "Qatari Rial" },
    "currency_ron": { "type": "string", "default": "Romanian Leu" },
    "currency_rsd": { "type": "string", "default": "Serbian Dinar" },
    "currency_rub": { "type": "string", "default": "Russian Ruble" },
    "currency_rwf": { "type": "string", "default": "Rwandan Franc" },
    "currency_sar": { "type": "string", "default": "Saudi Riyal" },
    "currency_sbd": { "type": "string", "default": "Solomon Islands Dollar" },
    "currency_scr": { "type": "string", "default": "Seychellois Rupee" },
    "currency_sdg": { "type": "string", "default": "Sudanese Pound" },
    "currency_sek": { "type": "string", "default": "Swedish Krona" },
    "currency_sgd": { "type": "string", "default": "Singapore Dollar" },
    "currency_shp": { "type": "string", "default": "Saint Helena Pound" },
    "currency_sll": { "type": "string", "default": "Sierra Leonean Leone" },
    "currency_sos": { "type": "string", "default": "Somali Shilling" },
    "currency_srd": { "type": "string", "default": "Surinamese Dollar" },
    "currency_ssp": { "type": "string", "default": "South Sudanese Pound" },
    "currency_std": { "type": "string", "default": "São Tomé and Príncipe Dobra (pre-2018)" },
    "currency_stn": { "type": "string", "default": "São Tomé and Príncipe Dobra" },
    "currency_svc": { "type": "string", "default": "Salvadoran Colón" },
    "currency_syp": { "type": "string", "default": "Syrian Pound" },
    "currency_szl": { "type": "string", "default": "Swazi Lilangeni" },
    "currency_thb": { "type": "string", "default": "Thai Baht" },
    "currency_tjs": { "type": "string", "default": "Tajikistani Somoni" },
    "currency_tmt": { "type": "string", "default": "Turkmenistani Manat" },
    "currency_tnd": { "type": "string", "default": "Tunisian Dinar" },
    "currency_top": { "type": "string", "default": "Tongan Pa'anga" },
    "currency_try": { "type": "string", "default": "Turkish Lira" },
    "currency_ttd": { "type": "string", "default": "Trinidad and Tobago Dollar" },
    "currency_twd": { "type": "string", "default": "New Taiwan Dollar" },
    "currency_tzs": { "type": "string", "default": "Tanzanian Shilling" },
    "currency_uah": { "type": "string", "default": "Ukrainian Hryvnia" },
    "currency_ugx": { "type": "string", "default": "Ugandan Shilling" },
    "currency_usd": { "type": "string", "default": "United States Dollar" },
    "currency_uyu": { "type": "string", "default": "Uruguayan Peso" },
    "currency_uzs": { "type": "string", "default": "Uzbekistan Som" },
    "currency_vef": { "type": "string", "default": "Venezuelan Bolívar Fuerte (Old)" },
    "currency_ves": { "type": "string", "default": "Venezuelan Bolívar Soberano" },
    "currency_vnd": { "type": "string", "default": "Vietnamese Dong" },
    "currency_vuv": { "type": "string", "default": "Vanuatu Vatu" },
    "currency_wst": { "type": "string", "default": "Samoan Tala" },
    "currency_xaf": { "type": "string", "default": "CFA Franc BEAC" },
    "currency_xag": { "type": "string", "default": "Silver Ounce" },
    "currency_xau": { "type": "string", "default": "Gold Ounce" },
    "currency_xcd": { "type": "string", "default": "East Caribbean Dollar" },
    "currency_xdr": { "type": "string", "default": "Special Drawing Rights" },
    "currency_xof": { "type": "string", "default": "CFA Franc BCEAO" },
    "currency_xpd": { "type": "string", "default": "Palladium Ounce" },
    "currency_xpf": { "type": "string", "default": "CFP Franc" },
    "currency_xpt": { "type": "string", "default": "Platinum Ounce" },
    "currency_yer": { "type": "string", "default": "Yemeni Rial" },
    "currency_zar": { "type": "string", "default": "South African Rand" },
    "currency_zmw": { "type": "string", "default": "Zambian Kwacha" },
    "currency_zwl": { "type": "string", "default": "Zimbabwean Dollar" },
    "current_balance": { "type": "string", "default": "Current balance" },
    "date": { "type": "string", "default": "{{value, date}}" },
    "date_created": { "type": "string", "default": "Created on" },
    "date_modified": { "type": "string", "default": "Last updated on" },
    "day": { "type": "string", "default": "Day" },
    "day_plural": { "type": "string", "default": "Days" },
    "delete": { "type": "string", "default": "Delete" },
    "delete_prompt": {
      "type": "string",
      "default": "This resource will be permanently removed. Are you sure?"
    },
    "end_date": { "type": "string", "default": "End date" },
    "expires": { "type": "string", "default": "Expires" },
    "expires_after": { "type": "string", "default": "Expires after" },
    "filter": { "type": "string", "default": "Filter" },
    "generate": { "type": "string", "default": "Generate" },
    "gift_card_category_restrictions_helper_text": {
      "type": "string",
      "default": "Select which item categories this gift card can be applied to. If you’d like this gift card to be available to all items regardless of the category, keep your selection empty. All changes are saved automatically."
    },
    "gift_card_name_helper_text": {
      "type": "string",
      "default": "Gift card names are displayed to the customer."
    },
    "gift_card_product_restrictions_explainer": {
      "type": "string",
      "default": "If you want to limit which products can use this gift card, you can enter full product codes or partial product codes using * as a wild card at the beginning or end of the value. So abc123, fun_*, *-small would match abc123, fun_ and fun_times, and example-small. It wouldn't match abc12, abc1234, fun, or good-smalls."
    },
    "import": { "type": "string", "default": "Import" },
    "month": { "type": "string", "default": "Month" },
    "month_plural": { "type": "string", "default": "Months" },
    "name": { "type": "string", "default": "Name" },
    "price": { "type": "string", "default": "{{amount, price}}" },
    "product_restrictions": { "type": "string", "default": "Product restrictions" },
    "save": { "type": "string", "default": "Save" },
    "select": { "type": "string", "default": "Select..." },
    "type_here": { "type": "string", "default": "Type here..." },
    "undo_cancel": { "type": "string", "default": "Review" },
    "undo_confirm": { "type": "string", "default": "Discard" },
    "undo_header": { "type": "string", "default": "Unsaved changes" },
    "undo_message": {
      "type": "string",
      "default": "Looks like you didn't save your changes! What would you like to do with them?"
    },
    "v8n_required": { "type": "string", "default": "Required" },
    "v8n_too_long": { "type": "string", "default": "Too long" },
    "week": { "type": "string", "default": "Week" },
    "week_plural": { "type": "string", "default": "Weeks" },
    "year": { "type": "string", "default": "Year" },
    "year_plural": { "type": "string", "default": "Years" },
    "provisioning": {
      "additionalProperties": false,
      "properties": {
        "toggle": {
          "additionalProperties": false,
          "properties": {
            "label": { "type": "string", "default": "Provisioning" },
            "text": { "type": "string", "default": "Allow customers to buy this gift card" },
            "helper_text": { "type": "string", "default": "" }
          },
          "required": ["label", "text", "helper_text"]
        },
        "sku": {
          "additionalProperties": false,
          "properties": {
            "label": { "type": "string", "default": "SKU" },
            "placeholder": { "type": "string", "default": "E.g. 100_usd" },
            "helper_text": {
              "type": "string",
              "default": "You'll use this value to add this gift card to a customer's online cart."
            },
            "v8n_required": { "type": "string", "default": "SKU is required for auto-provisioning" }
          },
          "required": ["label", "placeholder", "helper_text", "v8n_required"]
        },
        "min-balance": {
          "additionalProperties": false,
          "properties": {
            "label": { "type": "string", "default": "Min balance" },
            "placeholder": { "type": "string", "default": "0" },
            "helper_text": {
              "type": "string",
              "default": "Customers won't be able to load this card with a balance less than this value."
            },
            "v8n_negative": { "type": "string", "default": "Please enter a positive number" }
          },
          "required": ["label", "placeholder", "helper_text", "v8n_negative"]
        },
        "max-balance": {
          "additionalProperties": false,
          "properties": {
            "label": { "type": "string", "default": "Max balance" },
            "placeholder": { "type": "string", "default": "0" },
            "helper_text": {
              "type": "string",
              "default": "Customers won't be able to load this card with a balance greater than this value."
            },
            "v8n_negative": { "type": "string", "default": "Please enter a positive number" }
          },
          "required": ["label", "placeholder", "helper_text", "v8n_negative"]
        }
      },
      "required": ["toggle", "sku", "min-balance", "max-balance"]
    },
    "copy-to-clipboard": {
      "additionalProperties": false,
      "properties": {
        "click_to_copy": { "type": "string", "default": "Click to copy" },
        "copying": { "type": "string", "default": "Copying" },
        "done": { "type": "string", "default": "Done" },
        "failed_to_copy": { "type": "string", "default": "Failed to copy" }
      },
      "required": ["click_to_copy", "copying", "done", "failed_to_copy"]
    },
    "generate-codes-form": {
      "additionalProperties": false,
      "properties": {
        "balance": { "type": "string", "default": "Balance" },
        "cancel": { "type": "string", "default": "Cancel" },
        "confirm": { "type": "string", "default": "Confirm" },
        "current_balance": { "type": "string", "default": "Current balance" },
        "generate": { "type": "string", "default": "Generate" },
        "generate_codes_done": {
          "type": "string",
          "default": "All done! We've added new codes for you."
        },
        "leave_empty_for_random_codes": {
          "type": "string",
          "default": "Leave empty to generate completely random codes."
        },
        "length": { "type": "string", "default": "Length" },
        "number_of_codes": { "type": "string", "default": "Number of codes" },
        "prefix": { "type": "string", "default": "Prefix" },
        "template": { "type": "string", "default": "Template" },
        "v8n_negative": { "type": "string", "default": "Negative values are not allowed" },
        "v8n_required": { "type": "string", "default": "Required" },
        "spinner": {
          "additionalProperties": false,
          "properties": {
            "refresh": { "type": "string", "default": "Refresh" },
            "loading_busy": { "type": "string", "default": "Loading" },
            "loading_error": { "type": "string", "default": "Unknown error" }
          },
          "required": ["refresh", "loading_busy", "loading_error"]
        }
      },
      "required": [
        "balance",
        "cancel",
        "confirm",
        "current_balance",
        "generate",
        "generate_codes_done",
        "leave_empty_for_random_codes",
        "length",
        "number_of_codes",
        "prefix",
        "template",
        "v8n_negative",
        "v8n_required",
        "spinner"
      ]
    },
    "gift-card-code-form": {
      "additionalProperties": false,
      "properties": {
        "cancel": { "type": "string", "default": "Cancel" },
        "confirm": { "type": "string", "default": "Confirm" },
        "code": { "type": "string", "default": "Code" },
        "create": { "type": "string", "default": "Create" },
        "current_balance": { "type": "string", "default": "Current balance" },
        "date": { "type": "string", "default": "{{value, date}}" },
        "date_created": { "type": "string", "default": "Created on" },
        "date_modified": { "type": "string", "default": "Last updated on" },
        "delete": { "type": "string", "default": "Delete" },
        "delete_prompt": {
          "type": "string",
          "default": "This resource will be permanently removed. Are you sure?"
        },
        "end_date": { "type": "string", "default": "End date" },
        "v8n_required": { "type": "string", "default": "Required" },
        "v8n_too_long": { "type": "string", "default": "Too long" },
        "cart-item": {
          "additionalProperties": false,
          "properties": {
            "title": { "type": "string", "default": "Cart item" },
            "item-card": {
              "additionalProperties": false,
              "properties": {
                "price": { "type": "string", "default": "{{amount, price}}" },
                "wgt": { "type": "string", "default": "WGT" },
                "spinner": {
                  "additionalProperties": false,
                  "properties": {
                    "loading_busy": { "type": "string", "default": "Loading" },
                    "loading_empty": { "type": "string", "default": "No items" },
                    "loading_error": { "type": "string", "default": "Unknown error" }
                  },
                  "required": ["loading_busy", "loading_empty", "loading_error"]
                }
              },
              "required": ["price", "wgt", "spinner"]
            }
          },
          "required": ["title", "item-card"]
        },
        "logs": {
          "additionalProperties": false,
          "properties": {
            "title": { "type": "string", "default": "Timeline" },
            "pagination": {
              "additionalProperties": false,
              "properties": {
                "first": { "type": "string", "default": "First" },
                "last": { "type": "string", "default": "Last" },
                "next": { "type": "string", "default": "Next" },
                "pagination": { "type": "string", "default": "{{from}}-{{to}} out of {{total}}" },
                "previous": { "type": "string", "default": "Previous" },
                "card": {
                  "additionalProperties": false,
                  "properties": {
                    "status_updated_via_api": { "type": "string", "default": "Updated via API" },
                    "status_used": { "type": "string", "default": "Used on checkout" },
                    "title": { "type": "string", "default": "{{date, date}}" },
                    "spinner": {
                      "additionalProperties": false,
                      "properties": {
                        "loading_busy": { "type": "string", "default": "Loading" },
                        "loading_empty": { "type": "string", "default": "No data" },
                        "loading_error": { "type": "string", "default": "Unknown error" }
                      },
                      "required": ["loading_busy", "loading_empty", "loading_error"]
                    }
                  },
                  "required": ["status_updated_via_api", "status_used", "title", "spinner"]
                }
              },
              "required": ["first", "last", "next", "pagination", "previous", "card"]
            }
          },
          "required": ["title", "pagination"]
        },
        "spinner": {
          "additionalProperties": false,
          "properties": {
            "refresh": { "type": "string", "default": "Refresh" },
            "loading_busy": { "type": "string", "default": "Loading" },
            "loading_error": { "type": "string", "default": "Unknown error" }
          },
          "required": ["refresh", "loading_busy", "loading_error"]
        }
      },
      "required": [
        "cancel",
        "confirm",
        "code",
        "create",
        "current_balance",
        "date",
        "date_created",
        "date_modified",
        "delete",
        "delete_prompt",
        "end_date",
        "v8n_required",
        "v8n_too_long",
        "cart-item",
        "logs",
        "spinner"
      ]
    },
    "gift-card-codes-form": {
      "additionalProperties": false,
      "properties": {
        "balance": { "type": "string", "default": "Balance" },
        "cancel": { "type": "string", "default": "Cancel" },
        "code": { "type": "string", "default": "Code" },
        "code_import_hint": {
          "type": "string",
          "default": "Paste multiple space-separated codes in the field above to add all of them at once. Importing duplicate codes clears their usage stats."
        },
        "code_plural": { "type": "string", "default": "Codes" },
        "confirm": { "type": "string", "default": "Confirm" },
        "current_balance": { "type": "string", "default": "Current balance" },
        "duplicate": { "type": "string", "default": "Duplicate" },
        "hidden_codes_explainer": {
          "type": "string",
          "default": "We’ve hidden some of your codes because there were too many of them. Don’t worry – we’ll import them anyway."
        },
        "hidden_codes_header": { "type": "string", "default": "{{count}} code is hidden" },
        "hidden_codes_header_plural": { "type": "string", "default": "{{count}} codes are hidden" },
        "import": { "type": "string", "default": "Import" },
        "import_codes_done": {
          "type": "string",
          "default": "All done! We've imported your codes into the system."
        },
        "loading_busy": { "type": "string", "default": "Loading" },
        "loading_error": { "type": "string", "default": "Unknown error" },
        "type_here": { "type": "string", "default": "Type here..." },
        "unique": { "type": "string", "default": "Unique" },
        "v8n_negative": { "type": "string", "default": "Negative values are not allowed" },
        "v8n_required": { "type": "string", "default": "Required" },
        "spinner": {
          "additionalProperties": false,
          "properties": {
            "refresh": { "type": "string", "default": "Refresh" },
            "loading_busy": { "type": "string", "default": "Loading" },
            "loading_error": { "type": "string", "default": "Unknown error" }
          },
          "required": ["refresh", "loading_busy", "loading_error"]
        }
      },
      "required": [
        "balance",
        "cancel",
        "code",
        "code_import_hint",
        "code_plural",
        "confirm",
        "current_balance",
        "duplicate",
        "hidden_codes_explainer",
        "hidden_codes_header",
        "hidden_codes_header_plural",
        "import",
        "import_codes_done",
        "loading_busy",
        "loading_error",
        "type_here",
        "unique",
        "v8n_negative",
        "v8n_required",
        "spinner"
      ]
    },
    "pagination": {
      "additionalProperties": false,
      "properties": {
        "first": { "type": "string", "default": "First" },
        "last": { "type": "string", "default": "Last" },
        "next": { "type": "string", "default": "Next" },
        "pagination": { "type": "string", "default": "{{from}}-{{to}} out of {{total}}" },
        "previous": { "type": "string", "default": "Previous" }
      },
      "required": ["first", "last", "next", "pagination", "previous"]
    },
    "query-builder": {
      "additionalProperties": false,
      "properties": {
        "add_or_clause": { "type": "string", "default": "Add OR clause" },
        "add_value": { "type": "string", "default": "Add value" },
        "code": { "type": "string", "default": "Code" },
        "current_balance": { "type": "string", "default": "Current balance" },
        "date": { "type": "string", "default": "{{value, date}}" },
        "date_created": { "type": "string", "default": "Created on" },
        "date_modified": { "type": "string", "default": "Last updated on" },
        "delete": { "type": "string", "default": "Delete" },
        "end_date": { "type": "string", "default": "End date" },
        "field": { "type": "string", "default": "Field" },
        "hidden": { "type": "string", "default": "Hidden" },
        "is_defined_false": { "type": "string", "default": "Not defined" },
        "is_defined_true": { "type": "string", "default": "Defined" },
        "name": { "type": "string", "default": "Name" },
        "operator_equal": { "type": "string", "default": "Equal" },
        "operator_greaterthan": { "type": "string", "default": "Greater than" },
        "operator_greaterthanorequal": { "type": "string", "default": "Greater than or equal" },
        "operator_in": { "type": "string", "default": "One of" },
        "operator_isdefined": { "type": "string", "default": "Is defined" },
        "operator_lessthan": { "type": "string", "default": "Less than" },
        "operator_lessthanorequal": { "type": "string", "default": "Less than or equal" },
        "operator_not": { "type": "string", "default": "Not equal" },
        "or": { "type": "string", "default": "Or" },
        "query_builder_group": { "type": "string", "default": "Group of filters" },
        "query_builder_rule": { "type": "string", "default": "Filter" },
        "range_from": { "type": "string", "default": "From" },
        "range_to": { "type": "string", "default": "To" },
        "type": { "type": "string", "default": "Type" },
        "type_any": { "type": "string", "default": "Field of unknown type" },
        "type_attribute": { "type": "string", "default": "Key-value resource" },
        "type_date": { "type": "string", "default": "Date field" },
        "type_here": { "type": "string", "default": "Type here..." },
        "type_number": { "type": "string", "default": "Numeric field" },
        "type_string": { "type": "string", "default": "Text field" },
        "value": { "type": "string", "default": "Value" }
      },
      "required": [
        "add_or_clause",
        "add_value",
        "code",
        "current_balance",
        "date",
        "date_created",
        "date_modified",
        "delete",
        "end_date",
        "field",
        "hidden",
        "is_defined_false",
        "is_defined_true",
        "name",
        "operator_equal",
        "operator_greaterthan",
        "operator_greaterthanorequal",
        "operator_in",
        "operator_isdefined",
        "operator_lessthan",
        "operator_lessthanorequal",
        "operator_not",
        "or",
        "query_builder_group",
        "query_builder_rule",
        "range_from",
        "range_to",
        "type",
        "type_any",
        "type_attribute",
        "type_date",
        "type_here",
        "type_number",
        "type_string",
        "value"
      ]
    },
    "spinner": {
      "additionalProperties": false,
      "properties": {
        "refresh": { "type": "string", "default": "Refresh" },
        "loading_busy": { "type": "string", "default": "Loading" },
        "loading_error": { "type": "string", "default": "Unknown error" }
      },
      "required": ["refresh", "loading_busy", "loading_error"]
    }
  },
  "required": [
    "allow",
    "block",
    "cancel",
    "category_restrictions",
    "clear_filters",
    "close",
    "code",
    "code_plural",
    "confirm",
    "create",
    "currency",
    "currency_aed",
    "currency_afn",
    "currency_all",
    "currency_amd",
    "currency_ang",
    "currency_aoa",
    "currency_ars",
    "currency_aud",
    "currency_awg",
    "currency_azn",
    "currency_bam",
    "currency_bbd",
    "currency_bdt",
    "currency_bgn",
    "currency_bhd",
    "currency_bif",
    "currency_bmd",
    "currency_bnd",
    "currency_bob",
    "currency_brl",
    "currency_bsd",
    "currency_btc",
    "currency_btn",
    "currency_bwp",
    "currency_byn",
    "currency_bzd",
    "currency_cad",
    "currency_cdf",
    "currency_chf",
    "currency_clf",
    "currency_clp",
    "currency_cnh",
    "currency_cny",
    "currency_cop",
    "currency_crc",
    "currency_cuc",
    "currency_cup",
    "currency_cve",
    "currency_czk",
    "currency_djf",
    "currency_dkk",
    "currency_dop",
    "currency_dzd",
    "currency_egp",
    "currency_ern",
    "currency_etb",
    "currency_eur",
    "currency_fjd",
    "currency_fkp",
    "currency_gbp",
    "currency_gel",
    "currency_ggp",
    "currency_ghs",
    "currency_gip",
    "currency_gmd",
    "currency_gnf",
    "currency_gtq",
    "currency_gyd",
    "currency_hkd",
    "currency_hnl",
    "currency_hrk",
    "currency_htg",
    "currency_huf",
    "currency_idr",
    "currency_ils",
    "currency_imp",
    "currency_inr",
    "currency_iqd",
    "currency_irr",
    "currency_isk",
    "currency_jep",
    "currency_jmd",
    "currency_jod",
    "currency_jpy",
    "currency_kes",
    "currency_kgs",
    "currency_khr",
    "currency_kmf",
    "currency_kpw",
    "currency_krw",
    "currency_kwd",
    "currency_kyd",
    "currency_kzt",
    "currency_lak",
    "currency_lbp",
    "currency_lkr",
    "currency_lrd",
    "currency_lsl",
    "currency_lyd",
    "currency_mad",
    "currency_mdl",
    "currency_mga",
    "currency_mkd",
    "currency_mmk",
    "currency_mnt",
    "currency_mop",
    "currency_mru",
    "currency_mur",
    "currency_mvr",
    "currency_mwk",
    "currency_mxn",
    "currency_myr",
    "currency_mzn",
    "currency_nad",
    "currency_ngn",
    "currency_nio",
    "currency_nok",
    "currency_npr",
    "currency_nzd",
    "currency_omr",
    "currency_pab",
    "currency_pen",
    "currency_pgk",
    "currency_php",
    "currency_pkr",
    "currency_pln",
    "currency_pyg",
    "currency_qar",
    "currency_ron",
    "currency_rsd",
    "currency_rub",
    "currency_rwf",
    "currency_sar",
    "currency_sbd",
    "currency_scr",
    "currency_sdg",
    "currency_sek",
    "currency_sgd",
    "currency_shp",
    "currency_sll",
    "currency_sos",
    "currency_srd",
    "currency_ssp",
    "currency_std",
    "currency_stn",
    "currency_svc",
    "currency_syp",
    "currency_szl",
    "currency_thb",
    "currency_tjs",
    "currency_tmt",
    "currency_tnd",
    "currency_top",
    "currency_try",
    "currency_ttd",
    "currency_twd",
    "currency_tzs",
    "currency_uah",
    "currency_ugx",
    "currency_usd",
    "currency_uyu",
    "currency_uzs",
    "currency_vef",
    "currency_ves",
    "currency_vnd",
    "currency_vuv",
    "currency_wst",
    "currency_xaf",
    "currency_xag",
    "currency_xau",
    "currency_xcd",
    "currency_xdr",
    "currency_xof",
    "currency_xpd",
    "currency_xpf",
    "currency_xpt",
    "currency_yer",
    "currency_zar",
    "currency_zmw",
    "currency_zwl",
    "current_balance",
    "date",
    "date_created",
    "date_modified",
    "day",
    "day_plural",
    "delete",
    "delete_prompt",
    "end_date",
    "expires",
    "expires_after",
    "filter",
    "generate",
    "gift_card_category_restrictions_helper_text",
    "gift_card_name_helper_text",
    "gift_card_product_restrictions_explainer",
    "import",
    "month",
    "month_plural",
    "name",
    "price",
    "product_restrictions",
    "save",
    "select",
    "type_here",
    "undo_cancel",
    "undo_confirm",
    "undo_header",
    "undo_message",
    "v8n_required",
    "v8n_too_long",
    "week",
    "week_plural",
    "year",
    "year_plural",
    "provisioning",
    "copy-to-clipboard",
    "generate-codes-form",
    "gift-card-code-form",
    "gift-card-codes-form",
    "pagination",
    "query-builder",
    "spinner"
  ]
}
